py3grads/__init__.py
py3grads/gacore.py
py3grads-2024.5.11.dist-info/METADATA
py3grads-2024.5.11.dist-info/WHEEL
py3grads-2024.5.11.dist-info/top_level.txt
py3grads-2024.5.11.dist-info/RECORD
